assets/csv_output_example.png
assets/gcc_recorder_help.png
assets/lsusb_excerpt.png
src/GCCRecorder/__init__.py
src/GCCRecorder/core.py
src/GCCRecorder/gc_conversion.py
src/GCCRecorder/usb_stream_processer.py
src/GCCRecorder/usb_stream_reader.py
src/GCCRecorder/usb_stream_recorder.py
src/GCCRecorder/user_interface.py
gcc_recorder-1.0.0.dist-info/LICENSE
gcc_recorder-1.0.0.dist-info/METADATA
gcc_recorder-1.0.0.dist-info/WHEEL
gcc_recorder-1.0.0.dist-info/entry_points.txt
gcc_recorder-1.0.0.dist-info/top_level.txt
gcc_recorder-1.0.0.dist-info/RECORD
