Metadata-Version: 2.1
Name: gcc_recorder
Version: 1.0.0
Summary: Captures USB traffic from a Gamecube-to-USB adapter
Author: Ohayon Benjamin
License: GNU GENERAL PUBLIC LICENSE
Project-URL: Homepage, https://github.com/byohano/gcc_recorder
Keywords: gamecube,adapter,controller,capture,record,macro,packet,usb,snooping
Classifier: Development Status :: 4 - Beta
Classifier: Environment :: Console
Classifier: Intended Audience :: End Users/Desktop
Classifier: License :: OSI Approved :: GNU General Public License v3 (GPLv3)
Classifier: Natural Language :: English
Classifier: Operating System :: POSIX :: Linux
Classifier: Programming Language :: Python :: Implementation :: PyPy
Classifier: Topic :: System :: Hardware :: Universal Serial Bus (USB)
License-File: LICENSE
Requires-Dist: questionary
Requires-Dist: click
Provides-Extra: test
Requires-Dist: ruff ; extra == 'test'
Requires-Dist: isort ; extra == 'test'
Requires-Dist: pre-commit ; extra == 'test'
